{"cookies": [{"name": "sessionid", "value": "BgAAKy8t817cSXn23Z3ZHeqvVINiJWyphq4QvXLvt9zHB7jlA6BY8xuVyYnz68O5UOJWWb4d9hw%2B20LUXj7NNrdLcWfzlwBiSJuzhau1dQzI", "domain": "channels.weixin.qq.com", "path": "/", "expires": 1792317701.471532, "httpOnly": false, "secure": true, "sameSite": "None"}, {"name": "wxuin", "value": "3162055213", "domain": "channels.weixin.qq.com", "path": "/", "expires": 1792317701.471618, "httpOnly": false, "secure": true, "sameSite": "None"}], "origins": [{"origin": "https://channels.weixin.qq.com", "localStorage": [{"name": "finder_uin", "value": ""}, {"name": "finder_username", "value": "v2_060000231003b20faec8c5e08c1ccad1cd03e935b0773437b0136ebe1b25eae8eaf86129a2e0@finder"}, {"name": "__ml::hb_ts", "value": "1757757686125"}, {"name": "__ml::page_7ba70387-2c32-4878-89fb-1ce43d4735d2", "value": "{\"pageId\":\"LoginForIframe\",\"accessId\":\"92e1e732-1db8-4c55-a1fe-4c9c26afacbb\",\"step\":1}"}, {"name": "_finger_print_device_id", "value": "d1e5a26f358f84c2d8dfca332a070ed8"}, {"name": "__ml::aid", "value": "\"bcb205a0-dbd9-48d6-8859-04b23b8d058c\""}, {"name": "__rx::aid", "value": "\"bcb205a0-dbd9-48d6-8859-04b23b8d058c\""}, {"name": "UvFirstReportLocalKey", "value": "1757692800000"}, {"name": "__ml::page", "value": "[\"7ba70387-2c32-4878-89fb-1ce43d4735d2\"]"}, {"name": "finder_login_token", "value": ""}, {"name": "finder_ua_report_data", "value": "{\"browser\":\"Chrome\",\"browserVersion\":\"136.0.0.0\",\"engine\":\"Webkit\",\"engineVersion\":\"537.36\",\"os\":\"Mac OS X\",\"osVersion\":\"10.15.7\",\"device\":\"desktop\",\"darkmode\":0}"}, {"name": "finder_route_meta", "value": "platform;index;2;1757757703953"}]}]}